simet/cli/__init__.py
simet/cli/cli.py
simet/dataset_loaders/__init__.py
simet/dataset_loaders/dataset_loader.py
simet/datasets/__init__.py
simet/datasets/binary_folder_dataset.py
simet/datasets/no_class_image_dataset.py
simet/feature_extractor/__init__.py
simet/feature_extractor/feature_extractor.py
simet/feature_extractor/inception.py
simet/log/__init__.py
simet/log/log.json
simet/log/logger.py
simet/metrics/__init__.py
simet/metrics/fid.py
simet/metrics/precision_recall.py
simet/metrics/base/__init__.py
simet/metrics/base/metric.py
simet/metrics/downstream_task/__init__.py
simet/metrics/downstream_task/base/__init__.py
simet/metrics/downstream_task/base/downstream_task.py
simet/metrics/downstream_task/sample/__init__.py
simet/metrics/downstream_task/sample/sample_downstream_task.py
simet/metrics/downstream_task/sample/sample_trts.py
simet/metrics/downstream_task/sample/sample_tstr.py
simet/metrics/roc_auc/__init__.py
simet/metrics/roc_auc/mlp.py
simet/metrics/roc_auc/roc_auc.py
simet/models/__init__.py
simet/models/sample_simple_cnn.py
simet/parser/__init__.py
simet/parser/feature_extractor.py
simet/parser/provider.py
simet/parser/restraint.py
simet/parser/transform.py
simet/parser/simple/__init__.py
simet/parser/simple/metric.py
simet/parser/simple/provider.py
simet/pipeline/__init__.py
simet/pipeline/pipeline.py
simet/pipeline/simple_pipeline.py
simet/providers/__init__.py
simet/providers/cifar.py
simet/providers/local_binary_provider.py
simet/providers/local_provider_class.py
simet/providers/local_provider_no_class.py
simet/providers/subsampled_provider.py
simet/providers/base/__init__.py
simet/providers/base/provider.py
simet/restraints/__init__.py
simet/restraints/fid.py
simet/restraints/precision_recall.py
simet/restraints/roc_auc.py
simet/restraints/base/__init__.py
simet/restraints/base/restraint.py
simet/restraints/downstream_task/__init__.py
simet/restraints/downstream_task/sample_trts.py
simet/restraints/downstream_task/sample_tstr.py
simet-1.0.0.post1.dist-info/licenses/LICENSE.txt
simet-1.0.0.post1.dist-info/METADATA
simet-1.0.0.post1.dist-info/WHEEL
simet-1.0.0.post1.dist-info/entry_points.txt
simet-1.0.0.post1.dist-info/top_level.txt
simet-1.0.0.post1.dist-info/RECORD
