Metadata-Version: 2.4
Name: simet
Version: 1.0.0.post1
Summary: Synthetic image metrics - An evaluation framework for your synthetic images
Author-email: Oriol Agost Batalla <oriol.agost@udl.cat>, Oriol Agost Batalla <oriol.agost@gft.com>
Project-URL: Homepage, https://github.com/dcg-udl-cat/simet
Project-URL: Documentation, https://simet.udl.cat
Project-URL: Source, https://github.com/dcg-udl-cat/simet
Project-URL: Issues, https://github.com/dcg-udl-cat/simet/issues
Classifier: Intended Audience :: Science/Research
Classifier: Intended Audience :: Education
Classifier: License :: OSI Approved :: MIT License
Classifier: Operating System :: POSIX :: Linux
Classifier: Programming Language :: Python :: 3.12
Classifier: Programming Language :: Python :: 3 :: Only
Classifier: Topic :: Software Development :: Libraries
Classifier: Topic :: Scientific/Engineering :: Artificial Intelligence
Classifier: Topic :: Utilities
Requires-Python: ~=3.12.0
License-File: LICENSE.txt
Requires-Dist: faiss-gpu-cu12[fix-cuda]>=1.11.0
Requires-Dist: kagglehub>=0.3.12
Requires-Dist: pyyaml>=6.0.2
Requires-Dist: scikit-learn>=1.7.1
Requires-Dist: torch>=2.4.1
Requires-Dist: torchvision>=0.19.1
Requires-Dist: typer>=0.19.2
Dynamic: license-file
